rl_compression/RLD.py
rl_compression/RLE.py
rl_compression/__init__.py
rl_compression-0.1.3.dist-info/licenses/LICENSE
rl_compression-0.1.3.dist-info/METADATA
rl_compression-0.1.3.dist-info/WHEEL
rl_compression-0.1.3.dist-info/top_level.txt
rl_compression-0.1.3.dist-info/RECORD
