Metadata-Version: 2.4
Name: rl-compression
Version: 0.1.3
Summary: A simple run-length encoding/decoding compression library.
Author-email: Malek Yehya <malekyehya1@gmail.com>
License: MIT
Project-URL: Homepage, https://github.com/th3f0rk/rl_compression.git
Keywords: compression,RLE,run-length,python
Classifier: Programming Language :: Python :: 3
Classifier: License :: OSI Approved :: MIT License
Classifier: Operating System :: OS Independent
Requires-Python: >=3.8
License-File: LICENSE
Dynamic: license-file
